funda_scraper_private/__init__.py
funda_scraper_private/config/__init__.py
funda_scraper_private/config/config.yaml
funda_scraper_private/config/core.py
funda_scraper_private/preprocess.py
funda_scraper_private/scrape.py
funda_scraper_private/utils.py
funda_scraper_private/VERSION
funda_scraper_private-1.2.1.dist-info/LICENSE
funda_scraper_private-1.2.1.dist-info/METADATA
funda_scraper_private-1.2.1.dist-info/WHEEL
funda_scraper_private-1.2.1.dist-info/RECORD
