Metadata-Version: 2.3
Name: funda-scraper-private
Version: 1.2.1
Summary: FundaScaper provides the easiest way to perform web scraping on Funda, the Dutch housing website. You can find houses either for sale or for rent, and access historical data from the past few years.
Author: Will Chien
Requires-Python: >=3.8,<4.0
Classifier: Programming Language :: Python :: 3
Classifier: Programming Language :: Python :: 3.8
Classifier: Programming Language :: Python :: 3.9
Classifier: Programming Language :: Python :: 3.10
Classifier: Programming Language :: Python :: 3.11
Classifier: Programming Language :: Python :: 3.12
Classifier: Programming Language :: Python :: 3.13
Requires-Dist: beautifulsoup4 (>=4.8.0,<4.9.0)
Requires-Dist: diot (>=0.1.6,<0.2.0)
Requires-Dist: lxml (>=5.3.0,<6.0.0)
Requires-Dist: pandas (>=2.0.3,<2.1.0)
Requires-Dist: python-dateutil (>=2.8.2,<2.9.0)
Requires-Dist: pyyaml (>=6.0,<7.0)
Requires-Dist: requests (>=2.28.1,<2.29.0)
Requires-Dist: setuptools (>=61.3.1,<61.4.0)
Requires-Dist: tqdm (>=4.64.1,<4.65.0)
